setup.py
src/ore/__init__.py
src/ore.dtmlview.egg-info/PKG-INFO
src/ore.dtmlview.egg-info/SOURCES.txt
src/ore.dtmlview.egg-info/dependency_links.txt
src/ore.dtmlview.egg-info/namespace_packages.txt
src/ore.dtmlview.egg-info/not-zip-safe
src/ore.dtmlview.egg-info/requires.txt
src/ore.dtmlview.egg-info/top_level.txt
src/ore/dtmlview/__init__.py
src/ore/dtmlview/dtmlview.py
src/ore/dtmlview/tests/__init__.py
src/ore/dtmlview/tests/sample.py
src/ore/dtmlview/tests/test.dtml
src/ore/dtmlview/tests/test.js