Metadata-Version: 1.0
Name: ore.dtmlview
Version: 0.6.1
Summary: classic DTML useable as Zope3
Home-page: UNKNOWN
Author: ObjectRealms, LLC
Author-email: info@objectrealms.net
License: ZPL
Keywords: zope zope3
Platform: UNKNOWN
